<?xml version="1.0" encoding="utf-8"?><asx:abap xmlns:asx="http://www.sap.com/abapxml">
<asx:values>
<OBJH>
<OBJH>
<OBJECTNAME>SUSH</OBJECTNAME>
<OBJECTTYPE>L</OBJECTTYPE>
<CLIDEP></CLIDEP>
<LANGDEP>X</LANGDEP>
<ALEDEP></ALEDEP>
<OBJCATEG>SYST</OBJCATEG>
<TRCOMPLETE></TRCOMPLETE>
<TRDISJUNCT></TRDISJUNCT>
<PHASELEVEL>0</PHASELEVEL>
<LOCKMETH></LOCKMETH>
<TADIRCMETH></TADIRCMETH>
<CHECKID>L</CHECKID>
<OBJNAMELEN>32</OBJNAMELEN>
<PROTECT></PROTECT>
<OBJTRANSP>2</OBJTRANSP>
<LUSER>SAP</LUSER>
<LDATE>2019-04-08</LDATE>
<OBJNAMECLS></OBJNAMECLS>
<CURSETTING></CURSETTING>
<OBJHASADDR></OBJHASADDR>
<IMPORTABLE></IMPORTABLE>
<OBJCHARSET>1</OBJCHARSET>
<MCCATEGORY></MCCATEGORY>
<MCDOCUID></MCDOCUID>
</OBJH>
</OBJH>
<OBJS>
<OBJS>
<OBJECTNAME>SUSH</OBJECTNAME>
<OBJECTTYPE>L</OBJECTTYPE>
<TABNAME>SU2X_TEXT</TABNAME>
<COVER></COVER>
<CANDIDATE></CANDIDATE>
<DDIC>X</DDIC>
<PRIM_TABLE></PRIM_TABLE>
<VIEWGRANT></VIEWGRANT>
<TAB_FILLED></TAB_FILLED>
</OBJS>
<OBJS>
<OBJECTNAME>SUSH</OBJECTNAME>
<OBJECTTYPE>L</OBJECTTYPE>
<TABNAME>USOBHASH</TABNAME>
<COVER></COVER>
<CANDIDATE></CANDIDATE>
<DDIC>X</DDIC>
<PRIM_TABLE>X</PRIM_TABLE>
<VIEWGRANT></VIEWGRANT>
<TAB_FILLED></TAB_FILLED>
</OBJS>
<OBJS>
<OBJECTNAME>SUSH</OBJECTNAME>
<OBJECTTYPE>L</OBJECTTYPE>
<TABNAME>USOBT</TABNAME>
<COVER></COVER>
<CANDIDATE></CANDIDATE>
<DDIC>X</DDIC>
<PRIM_TABLE></PRIM_TABLE>
<VIEWGRANT></VIEWGRANT>
<TAB_FILLED></TAB_FILLED>
</OBJS>
<OBJS>
<OBJECTNAME>SUSH</OBJECTNAME>
<OBJECTTYPE>L</OBJECTTYPE>
<TABNAME>USOBX</TABNAME>
<COVER></COVER>
<CANDIDATE></CANDIDATE>
<DDIC>X</DDIC>
<PRIM_TABLE></PRIM_TABLE>
<VIEWGRANT></VIEWGRANT>
<TAB_FILLED></TAB_FILLED>
</OBJS>
<OBJS>
<OBJECTNAME>SUSH</OBJECTNAME>
<OBJECTTYPE>L</OBJECTTYPE>
<TABNAME>USOB_SM</TABNAME>
<COVER></COVER>
<CANDIDATE></CANDIDATE>
<DDIC>X</DDIC>
<PRIM_TABLE></PRIM_TABLE>
<VIEWGRANT></VIEWGRANT>
<TAB_FILLED></TAB_FILLED>
</OBJS>
<OBJS>
<OBJECTNAME>SUSH</OBJECTNAME>
<OBJECTTYPE>L</OBJECTTYPE>
<TABNAME>USOTT</TABNAME>
<COVER></COVER>
<CANDIDATE></CANDIDATE>
<DDIC>X</DDIC>
<PRIM_TABLE></PRIM_TABLE>
<VIEWGRANT></VIEWGRANT>
<TAB_FILLED></TAB_FILLED>
</OBJS>
</OBJS>
<OBJSL>
<OBJSL>
<OBJECTNAME>SUSH</OBJECTNAME>
<OBJECTTYPE>L</OBJECTTYPE>
<TRWCOUNT>01</TRWCOUNT>
<TPGMID>R3TR</TPGMID>
<TOBJECT>TABU</TOBJECT>
<TOBJ_NAME>USOBHASH</TOBJ_NAME>
<TOBJKEY>/&amp;</TOBJKEY>
<MASKNLEN>8</MASKNLEN>
<MASKKLEN>1</MASKKLEN>
<PRIM_TABLE>X</PRIM_TABLE>
</OBJSL>
<OBJSL>
<OBJECTNAME>SUSH</OBJECTNAME>
<OBJECTTYPE>L</OBJECTTYPE>
<TRWCOUNT>02</TRWCOUNT>
<TPGMID>R3TR</TPGMID>
<TOBJECT>TABU</TOBJECT>
<TOBJ_NAME>USOBT</TOBJ_NAME>
<TOBJKEY>/&amp;/*</TOBJKEY>
<MASKNLEN>5</MASKNLEN>
<MASKKLEN>2</MASKKLEN>
<PRIM_TABLE></PRIM_TABLE>
</OBJSL>
<OBJSL>
<OBJECTNAME>SUSH</OBJECTNAME>
<OBJECTTYPE>L</OBJECTTYPE>
<TRWCOUNT>03</TRWCOUNT>
<TPGMID>R3TR</TPGMID>
<TOBJECT>TABU</TOBJECT>
<TOBJ_NAME>USOTT</TOBJ_NAME>
<TOBJKEY>/&amp;/*</TOBJKEY>
<MASKNLEN>5</MASKNLEN>
<MASKKLEN>2</MASKKLEN>
<PRIM_TABLE></PRIM_TABLE>
</OBJSL>
<OBJSL>
<OBJECTNAME>SUSH</OBJECTNAME>
<OBJECTTYPE>L</OBJECTTYPE>
<TRWCOUNT>04</TRWCOUNT>
<TPGMID>R3TR</TPGMID>
<TOBJECT>TABU</TOBJECT>
<TOBJ_NAME>USOBX</TOBJ_NAME>
<TOBJKEY>/&amp;/*</TOBJKEY>
<MASKNLEN>5</MASKNLEN>
<MASKKLEN>2</MASKKLEN>
<PRIM_TABLE></PRIM_TABLE>
</OBJSL>
<OBJSL>
<OBJECTNAME>SUSH</OBJECTNAME>
<OBJECTTYPE>L</OBJECTTYPE>
<TRWCOUNT>05</TRWCOUNT>
<TPGMID>R3TR</TPGMID>
<TOBJECT>TABU</TOBJECT>
<TOBJ_NAME>USOB_SM</TOBJ_NAME>
<TOBJKEY>/&amp;</TOBJKEY>
<MASKNLEN>7</MASKNLEN>
<MASKKLEN>1</MASKKLEN>
<PRIM_TABLE></PRIM_TABLE>
</OBJSL>
<OBJSL>
<OBJECTNAME>SUSH</OBJECTNAME>
<OBJECTTYPE>L</OBJECTTYPE>
<TRWCOUNT>06</TRWCOUNT>
<TPGMID>R3TR</TPGMID>
<TOBJECT>TABU</TOBJECT>
<TOBJ_NAME>SU2X_TEXT</TOBJ_NAME>
<TOBJKEY>/L/&amp;/*</TOBJKEY>
<MASKNLEN>9</MASKNLEN>
<MASKKLEN>3</MASKKLEN>
<PRIM_TABLE></PRIM_TABLE>
</OBJSL>
</OBJSL>
<OBJT>
<OBJT>
<LANGUAGE>8</LANGUAGE>
<OBJECTNAME>SUSH</OBJECTNAME>
<OBJECTTYPE>L</OBJECTTYPE>
<DDTEXT>Присвоювання: сервіс --&gt; об'єкти повноважень</DDTEXT>
</OBJT>
<OBJT>
<LANGUAGE>C</LANGUAGE>
<OBJECTNAME>SUSH</OBJECTNAME>
<OBJECTTYPE>L</OBJECTTYPE>
<DDTEXT>Přiřazení služba --&gt; objekty oprávnění</DDTEXT>
</OBJT>
<OBJT>
<LANGUAGE>D</LANGUAGE>
<OBJECTNAME>SUSH</OBJECTNAME>
<OBJECTTYPE>L</OBJECTTYPE>
<DDTEXT>Zuordnung Service --&gt; Ber.objekte</DDTEXT>
</OBJT>
<OBJT>
<LANGUAGE>E</LANGUAGE>
<OBJECTNAME>SUSH</OBJECTNAME>
<OBJECTTYPE>L</OBJECTTYPE>
<DDTEXT>Assignment: Service --&gt; Authorization Objects</DDTEXT>
</OBJT>
<OBJT>
<LANGUAGE>F</LANGUAGE>
<OBJECTNAME>SUSH</OBJECTNAME>
<OBJECTTYPE>L</OBJECTTYPE>
<DDTEXT>Affectation service --&gt; objets d'autorisation</DDTEXT>
</OBJT>
<OBJT>
<LANGUAGE>H</LANGUAGE>
<OBJECTNAME>SUSH</OBJECTNAME>
<OBJECTTYPE>L</OBJECTTYPE>
<DDTEXT>Szolgáltatás --&gt; jog.obj.-ok hozzárendelése</DDTEXT>
</OBJT>
<OBJT>
<LANGUAGE>I</LANGUAGE>
<OBJECTNAME>SUSH</OBJECTNAME>
<OBJECTTYPE>L</OBJECTTYPE>
<DDTEXT>Attribuzione servizio --&gt; oggetti di autorizzazione</DDTEXT>
</OBJT>
<OBJT>
<LANGUAGE>J</LANGUAGE>
<OBJECTNAME>SUSH</OBJECTNAME>
<OBJECTTYPE>L</OBJECTTYPE>
<DDTEXT>割当: サービス --&gt; 権限オブジェクト</DDTEXT>
</OBJT>
<OBJT>
<LANGUAGE>N</LANGUAGE>
<OBJECTNAME>SUSH</OBJECTNAME>
<OBJECTTYPE>L</OBJECTTYPE>
<DDTEXT>Toewijzing service --&gt; bevoegdheidsobjecten</DDTEXT>
</OBJT>
<OBJT>
<LANGUAGE>P</LANGUAGE>
<OBJECTNAME>SUSH</OBJECTNAME>
<OBJECTTYPE>L</OBJECTTYPE>
<DDTEXT>Atribuição serviço --&gt; objetos de autorização</DDTEXT>
</OBJT>
<OBJT>
<LANGUAGE>Q</LANGUAGE>
<OBJECTNAME>SUSH</OBJECTNAME>
<OBJECTTYPE>L</OBJECTTYPE>
<DDTEXT>Priradenie: Služba --&gt; objekty oprávnenia</DDTEXT>
</OBJT>
<OBJT>
<LANGUAGE>R</LANGUAGE>
<OBJECTNAME>SUSH</OBJECTNAME>
<OBJECTTYPE>L</OBJECTTYPE>
<DDTEXT>Присвоение сервис --&gt; объекты полномочий</DDTEXT>
</OBJT>
<OBJT>
<LANGUAGE>S</LANGUAGE>
<OBJECTNAME>SUSH</OBJECTNAME>
<OBJECTTYPE>L</OBJECTTYPE>
<DDTEXT>Asignación servicio --&gt; Objetos autorización</DDTEXT>
</OBJT>
</OBJT>
</asx:values>
</asx:abap>